pynq_peripherals/__init__.py
pynq_peripherals/cli.py
pynq_peripherals/apps/app0_plant_monitoring_system/notebooks/plant_monitoring_system.ipynb
pynq_peripherals/apps/app0_plant_monitoring_system/notebooks/images/dry_arduino.png
pynq_peripherals/apps/app1_room_control_system/notebooks/room_control_system.ipynb
pynq_peripherals/apps/app1_room_control_system/notebooks/images/rcs_ctl.png
pynq_peripherals/apps/app1_room_control_system/notebooks/images/room_clip.png
pynq_peripherals/apps/app1_room_control_system/notebooks/images/room_control.png
pynq_peripherals/apps/app2_led_strings/notebooks/led_strings.ipynb
pynq_peripherals/apps/app2_led_strings/notebooks/images/IMG_2204.jpg
pynq_peripherals/apps/app3_voice_enabled_room_control_system/notebooks/voice_enabled_room_control_system.ipynb
pynq_peripherals/apps/app3_voice_enabled_room_control_system/notebooks/data/check_internet.mp3
pynq_peripherals/apps/app3_voice_enabled_room_control_system/notebooks/data/room.png
pynq_peripherals/apps/app4_automatic_door_control_and_motion_logger/notebooks/automatic_door_control_and_motion_logger.ipynb
pynq_peripherals/apps/app4_automatic_door_control_and_motion_logger/notebooks/images/door_control.png
pynq_peripherals/apps/app5_pynq_car/notebooks/pynq_car.ipynb
pynq_peripherals/apps/app5_pynq_car/notebooks/images/BlackLight.png
pynq_peripherals/apps/app5_pynq_car/notebooks/images/map.png
pynq_peripherals/apps/app5_pynq_car/notebooks/images/motor_system.png
pynq_peripherals/apps/app5_pynq_car/notebooks/images/pynq_car.jpg
pynq_peripherals/apps/app5_pynq_car/notebooks/images/sensor_connection.png
pynq_peripherals/modules/analog/include/analog.h
pynq_peripherals/modules/analog/src/analog.c
pynq_peripherals/modules/geared_motor/include/geared_motor.h
pynq_peripherals/modules/geared_motor/notebooks/geared_motor.ipynb
pynq_peripherals/modules/geared_motor/src/geared_motor.c
pynq_peripherals/modules/grove_adc/include/grove_adc.h
pynq_peripherals/modules/grove_adc/notebooks/grove_adc.ipynb
pynq_peripherals_git-0.1.0.dist-info/licenses/LICENSE
pynq_peripherals_git-0.1.0.dist-info/METADATA
pynq_peripherals_git-0.1.0.dist-info/WHEEL
pynq_peripherals_git-0.1.0.dist-info/entry_points.txt
pynq_peripherals_git-0.1.0.dist-info/top_level.txt
pynq_peripherals_git-0.1.0.dist-info/RECORD
