Metadata-Version: 2.4
Name: pynq_peripherals-git
Version: 0.1.0
Summary: Driver packages for PYNQ Peripherals
Author: PYNQ Team
Author-email: pynq_support@xilinx.com
License: BSD
License-File: LICENSE
Requires-Dist: pynq>=2.6.2
Requires-Dist: simple_term_menu
Dynamic: author
Dynamic: author-email
Dynamic: license
Dynamic: license-file
Dynamic: requires-dist
Dynamic: summary
